[
  {
    "id": "CH-001",
    "titulo": "Sistema fora do ar - Impossível acessar plataforma",
    "descricao": "O sistema está completamente inacessível desde às 14h30. Nenhum usuário consegue fazer login ou acessar qualquer funcionalidade.",
    "prioridade": "crítico",
    "status": "novo",
    "categoria": "Sistema",
    "dataAbertura": "2025-11-15T14:30:00",
    "dataAtualizacao": "2025-11-15T15:45:00",
    "franqueado": "Unidade Centro - São Paulo",
    "responsavel": "Equipe Técnica",
    "tempoResolucao": null,
    "sla": "2025-11-15T16:30:00"
  },
  {
    "id": "CH-002",
    "titulo": "Reset de senha - Usuário não consegue acessar",
    "descricao": "Solicitação de reset de senha para o usuário joao.silva@franquia.com.br. O usuário esqueceu a senha e não consegue acessar o sistema.",
    "prioridade": "normal",
    "status": "em_andamento",
    "categoria": "Acesso",
    "dataAbertura": "2025-11-15T10:15:00",
    "dataAtualizacao": "2025-11-15T11:20:00",
    "franqueado": "Unidade Norte - Belo Horizonte",
    "responsavel": "Suporte Nível 1",
    "tempoResolucao": null,
    "sla": "2025-11-15T12:00:00"
  },
  {
    "id": "CH-003",
    "titulo": "Criação de acesso para novo funcionário",
    "descricao": "Necessário criar acesso completo para Maria Santos, nova recepcionista. Precisa de permissões para agendamento e cadastro de pacientes.",
    "prioridade": "normal",
    "status": "aguardando_retorno",
    "categoria": "Acesso",
    "dataAbertura": "2025-11-15T09:00:00",
    "dataAtualizacao": "2025-11-15T09:00:00",
    "franqueado": "Unidade Sul - Curitiba",
    "responsavel": "Administração",
    "tempoResolucao": null,
    "sla": "2025-11-16T18:00:00"
  },
  {
    "id": "CH-004",
    "titulo": "Dúvida sobre relatório de procedimentos",
    "descricao": "Como gerar o relatório mensal de procedimentos realizados? Não encontro a opção no menu de relatórios.",
    "prioridade": "baixa",
    "status": "concluido",
    "categoria": "Dúvida",
    "dataAbertura": "2025-11-15T08:30:00",
    "dataAtualizacao": "2025-11-15T08:30:00",
    "franqueado": "Unidade Leste - Rio de Janeiro",
    "responsavel": "Suporte Nível 1",
    "tempoResolucao": null,
    "sla": "2025-11-16T17:00:00"
  },
  {
    "id": "CH-005",
    "titulo": "Sistema não está registrando vendas",
    "descricao": "O sistema não está registrando nenhuma venda desde às 10h desta manhã. Todas as transações realizadas não estão sendo salvas no banco de dados. Impacto crítico nas operações.",
    "prioridade": "crítico",
    "status": "em_andamento",
    "categoria": "Sistema",
    "dataAbertura": "2025-11-15T13:00:00",
    "dataAtualizacao": "2025-11-15T14:15:00",
    "franqueado": "Unidade Oeste - Campinas",
    "responsavel": "Equipe Técnica",
    "tempoResolucao": null,
    "sla": "2025-11-15T17:00:00"
  },
  {
    "id": "CH-006",
    "titulo": "Alteração de permissões de usuário",
    "descricao": "Necessário alterar permissões do usuário carlos.oliveira@franquia.com.br para permitir acesso ao módulo financeiro.",
    "prioridade": "normal",
    "status": "novo",
    "categoria": "Acesso",
    "dataAbertura": "2025-11-15T11:00:00",
    "dataAtualizacao": "2025-11-15T11:00:00",
    "franqueado": "Unidade Centro - São Paulo",
    "responsavel": "Administração",
    "tempoResolucao": null,
    "sla": "2025-11-16T18:00:00"
  },
  {
    "id": "CH-007",
    "titulo": "Dúvida sobre cadastro de pacientes",
    "descricao": "Como cadastrar pacientes menores de idade? O sistema está pedindo CPF mas menores não possuem.",
    "prioridade": "baixa",
    "status": "aguardando_retorno",
    "categoria": "Dúvida",
    "dataAbertura": "2025-11-14T16:00:00",
    "dataAtualizacao": "2025-11-15T09:30:00",
    "franqueado": "Unidade Norte - Belo Horizonte",
    "responsavel": "Suporte Nível 1",
    "tempoResolucao": null,
    "sla": "2025-11-16T16:00:00"
  },
  {
    "id": "CH-008",
    "titulo": "Backup não está sendo executado automaticamente",
    "descricao": "O backup automático configurado para executar diariamente às 2h não está sendo realizado há 3 dias.",
    "prioridade": "normal",
    "status": "em_andamento",
    "categoria": "Sistema",
    "dataAbertura": "2025-11-15T07:00:00",
    "dataAtualizacao": "2025-11-15T10:00:00",
    "franqueado": "Unidade Sul - Curitiba",
    "responsavel": "Equipe Técnica",
    "tempoResolucao": null,
    "sla": "2025-11-16T12:00:00"
  },
  {
    "id": "CH-009",
    "titulo": "Solicitação de treinamento para novos funcionários",
    "descricao": "Precisamos de treinamento para 3 novos funcionários que iniciarão na próxima semana. Preferência para horário da manhã.",
    "prioridade": "baixa",
    "status": "novo",
    "categoria": "Treinamento",
    "dataAbertura": "2025-11-15T09:30:00",
    "dataAtualizacao": "2025-11-15T09:30:00",
    "franqueado": "Unidade Leste - Rio de Janeiro",
    "responsavel": "Suporte Nível 1",
    "tempoResolucao": null,
    "sla": "2025-11-20T18:00:00"
  },
  {
    "id": "CH-010",
    "titulo": "Erro ao exportar dados para Excel",
    "descricao": "Ao tentar exportar relatório de vendas para Excel, o arquivo gerado está corrompido e não abre corretamente.",
    "prioridade": "normal",
    "status": "concluido",
    "categoria": "Sistema",
    "dataAbertura": "2025-11-14T14:00:00",
    "dataAtualizacao": "2025-11-15T08:00:00",
    "franqueado": "Unidade Oeste - Campinas",
    "responsavel": "Equipe Técnica",
    "tempoResolucao": null,
    "sla": "2025-11-15T18:00:00"
  },
  {
    "id": "CH-011",
    "titulo": "Bloqueio de conta após múltiplas tentativas de login",
    "descricao": "Conta do usuário ana.costa@franquia.com.br foi bloqueada após 5 tentativas de login incorretas. Necessário desbloqueio.",
    "prioridade": "normal",
    "status": "novo",
    "categoria": "Acesso",
    "dataAbertura": "2025-11-15T12:00:00",
    "dataAtualizacao": "2025-11-15T12:00:00",
    "franqueado": "Unidade Centro - São Paulo",
    "responsavel": "Suporte Nível 1",
    "tempoResolucao": null,
    "sla": "2025-11-15T16:00:00"
  },
  {
    "id": "CH-012",
    "titulo": "Dúvida sobre configuração de agendamento",
    "descricao": "Como configurar horários de atendimento diferentes para cada profissional? Não consigo encontrar essa opção.",
    "prioridade": "baixa",
    "status": "aguardando_retorno",
    "categoria": "Dúvida",
    "dataAbertura": "2025-11-14T10:00:00",
    "dataAtualizacao": "2025-11-14T15:00:00",
    "franqueado": "Unidade Norte - Belo Horizonte",
    "responsavel": "Suporte Nível 1",
    "tempoResolucao": null,
    "sla": "2025-11-16T17:00:00"
  },
  {
    "id": "CH-013",
    "titulo": "Lentidão extrema no sistema durante picos de uso",
    "descricao": "O sistema fica extremamente lento entre 8h e 10h da manhã, período de maior movimento. Quase impossível trabalhar.",
    "prioridade": "crítico",
    "status": "em_andamento",
    "categoria": "Sistema",
    "dataAbertura": "2025-11-15T08:00:00",
    "dataAtualizacao": "2025-11-15T11:00:00",
    "franqueado": "Unidade Sul - Curitiba",
    "responsavel": "Equipe Técnica",
    "tempoResolucao": null,
    "sla": "2025-11-15T18:00:00"
  },
  {
    "id": "CH-014",
    "titulo": "Remoção de acesso de funcionário desligado",
    "descricao": "Funcionário Pedro Alves foi desligado da empresa. Necessário remover todos os acessos ao sistema imediatamente.",
    "prioridade": "normal",
    "status": "concluido",
    "categoria": "Acesso",
    "dataAbertura": "2025-11-15T07:30:00",
    "dataAtualizacao": "2025-11-15T08:00:00",
    "franqueado": "Unidade Leste - Rio de Janeiro",
    "responsavel": "Administração",
    "tempoResolucao": null,
    "sla": "2025-11-15T12:00:00"
  },
  {
    "id": "CH-015",
    "titulo": "Erro ao salvar alterações em prontuário",
    "descricao": "Ao tentar salvar alterações em um prontuário de paciente, aparece mensagem de erro genérico e as alterações não são salvas.",
    "prioridade": "normal",
    "status": "novo",
    "categoria": "Sistema",
    "dataAbertura": "2025-11-15T10:45:00",
    "dataAtualizacao": "2025-11-15T10:45:00",
    "franqueado": "Unidade Oeste - Campinas",
    "responsavel": "Equipe Técnica",
    "tempoResolucao": null,
    "sla": "2025-11-16T18:00:00"
  }
]

